videogram/__init__.py
videogram/helloworld.py
videogram-0.0.2.dist-info/LICENSE
videogram-0.0.2.dist-info/METADATA
videogram-0.0.2.dist-info/WHEEL
videogram-0.0.2.dist-info/top_level.txt
videogram-0.0.2.dist-info/RECORD
