Metadata-Version: 2.1
Name: videogram
Version: 0.0.2
Summary: Package for video processing.
Author: Ishan Dutta
Author-email: duttaishan0098@gmail.com
Keywords: python,video,stream,video processing,video editing,video recording
Classifier: Development Status :: 1 - Planning
Classifier: Intended Audience :: Developers
Classifier: Programming Language :: Python :: 3
Classifier: Operating System :: Unix
Classifier: Operating System :: MacOS :: MacOS X
Classifier: Operating System :: Microsoft :: Windows
License-File: LICENSE
